[
    {
        "Title":  "JUPITERS LEGACY",
        "Issue":  "1A",
        "Cover":  1,
        "TotalCost":  "3.09",
        "Mean":  3.0922222222222224,
        "AveragePrice":  2.2533333333333334,
        "CurrentPrice":  2.2700000000000005,
        "Minimum":  0.99,
        "Maximum":  3.99,
        "Count":  9,
        "AveragePaid":  null,
        "AverageNetPaid":  null,
        "Stock":  null
    },
    {
        "Title":  "JUPITERS LEGACY",
        "Issue":  "1A:SIGNED",
        "Cover":  1,
        "TotalCost":  "10.50",
        "Mean":  10.5,
        "AveragePrice":  9.5,
        "CurrentPrice":  9.5,
        "Minimum":  9.5,
        "Maximum":  9.5,
        "Count":  1,
        "AveragePaid":  null,
        "AverageNetPaid":  null,
        "Stock":  null
    },
    {
        "Title":  "JUPITERS LEGACY",
        "Issue":  "1B",
        "Cover":  1,
        "TotalCost":  "2.60",
        "Mean":  2.6,
        "AveragePrice":  2.1,
        "CurrentPrice":  2.1,
        "Minimum":  1.25,
        "Maximum":  2.95,
        "Count":  2,
        "AveragePaid":  null,
        "AverageNetPaid":  null,
        "Stock":  null
    },
    {
        "Title":  "JUPITERS LEGACY",
        "Issue":  "1C",
        "Cover":  1,
        "TotalCost":  "2.76",
        "Mean":  2.7625,
        "AveragePrice":  2.325,
        "CurrentPrice":  2.325,
        "Minimum":  1.5,
        "Maximum":  3.5,
        "Count":  4,
        "AveragePaid":  null,
        "AverageNetPaid":  null,
        "Stock":  null
    },
    {
        "Title":  "JUPITERS LEGACY",
        "Issue":  "1D",
        "Cover":  1,
        "TotalCost":  "2.10",
        "Mean":  2.0975,
        "AveragePrice":  1.5725,
        "CurrentPrice":  1.5725,
        "Minimum":  0.99,
        "Maximum":  2.25,
        "Count":  4,
        "AveragePaid":  2.09,
        "AverageNetPaid":  0.99,
        "Stock":  1
    },
    {
        "Title":  "JUPITERS LEGACY",
        "Issue":  "1E",
        "Cover":  1,
        "TotalCost":  "3.79",
        "Mean":  3.7940000000000005,
        "AveragePrice":  2.786,
        "CurrentPrice":  2.7860000000000005,
        "Minimum":  0.99,
        "Maximum":  4.99,
        "Count":  5,
        "AveragePaid":  null,
        "AverageNetPaid":  null,
        "Stock":  null
    },
    {
        "Title":  "JUPITERS LEGACY",
        "Issue":  "1F",
        "Cover":  1,
        "TotalCost":  "2.00",
        "Mean":  1.995,
        "AveragePrice":  1.545,
        "CurrentPrice":  1.545,
        "Minimum":  0.99,
        "Maximum":  2.1,
        "Count":  2,
        "AveragePaid":  2.1,
        "AverageNetPaid":  2.1,
        "Stock":  1
    },
    {
        "Title":  "JUPITERS LEGACY",
        "Issue":  "1FORPLA",
        "Cover":  1,
        "TotalCost":  "2.10",
        "Mean":  2.1,
        "AveragePrice":  2.1,
        "CurrentPrice":  2.1,
        "Minimum":  2.1,
        "Maximum":  2.1,
        "Count":  1,
        "AveragePaid":  2.1,
        "AverageNetPaid":  2.1,
        "Stock":  1
    },
    {
        "Title":  "JUPITERS LEGACY",
        "Issue":  "1FP",
        "Cover":  1,
        "TotalCost":  "3.79",
        "Mean":  3.7900000000000005,
        "AveragePrice":  2.8233333333333337,
        "CurrentPrice":  2.8233333333333337,
        "Minimum":  0.99,
        "Maximum":  5.99,
        "Count":  3,
        "AveragePaid":  null,
        "AverageNetPaid":  null,
        "Stock":  null
    },
    {
        "Title":  "JUPITERS LEGACY",
        "Issue":  "1G",
        "Cover":  1,
        "TotalCost":  "2.31",
        "Mean":  2.313333333333333,
        "AveragePrice":  1.9466666666666665,
        "CurrentPrice":  1.9466666666666665,
        "Minimum":  0.99,
        "Maximum":  2.95,
        "Count":  3,
        "AveragePaid":  null,
        "AverageNetPaid":  null,
        "Stock":  null
    },
    {
        "Title":  "JUPITERS LEGACY",
        "Issue":  "1GIANT",
        "Cover":  1,
        "TotalCost":  "3.33",
        "Mean":  3.3333333333333335,
        "AveragePrice":  3.3333333333333335,
        "CurrentPrice":  3.3333333333333335,
        "Minimum":  2.75,
        "Maximum":  4.5,
        "Count":  3,
        "AveragePaid":  null,
        "AverageNetPaid":  null,
        "Stock":  null
    },
    {
        "Title":  "JUPITERS LEGACY",
        "Issue":  "1MIDTOWN",
        "Cover":  1,
        "TotalCost":  "9.40",
        "Mean":  9.3999999999999986,
        "AveragePrice":  8.5874999999999986,
        "CurrentPrice":  8.5874999999999986,
        "Minimum":  5,
        "Maximum":  12.95,
        "Count":  4,
        "AveragePaid":  null,
        "AverageNetPaid":  null,
        "Stock":  null
    },
    {
        "Title":  "JUPITERS LEGACY",
        "Issue":  "1PHANTOM",
        "Cover":  1,
        "TotalCost":  "6.43",
        "Mean":  6.43,
        "AveragePrice":  4.9633333333333338,
        "CurrentPrice":  4.9633333333333338,
        "Minimum":  2.9,
        "Maximum":  6.99,
        "Count":  3,
        "AveragePaid":  null,
        "AverageNetPaid":  null,
        "Stock":  null
    },
    {
        "Title":  "JUPITERS LEGACY",
        "Issue":  "1SKETCH",
        "Cover":  1,
        "TotalCost":  "1.89",
        "Mean":  1.8900000000000001,
        "AveragePrice":  0.99,
        "CurrentPrice":  0.99,
        "Minimum":  0.99,
        "Maximum":  0.99,
        "Count":  2,
        "AveragePaid":  null,
        "AverageNetPaid":  null,
        "Stock":  null
    },
    {
        "Title":  "JUPITERS LEGACY",
        "Issue":  "1STUDIO",
        "Cover":  1,
        "TotalCost":  "2.76",
        "Mean":  2.76,
        "AveragePrice":  2.085,
        "CurrentPrice":  2.085,
        "Minimum":  0.6,
        "Maximum":  3.5,
        "Count":  4,
        "AveragePaid":  null,
        "AverageNetPaid":  null,
        "Stock":  null
    },
    {
        "Title":  "JUPITERS LEGACY",
        "Issue":  "2A",
        "Cover":  2,
        "TotalCost":  "3.19",
        "Mean":  3.18875,
        "AveragePrice":  2.29,
        "CurrentPrice":  2.648,
        "Minimum":  0.99,
        "Maximum":  3.99,
        "Count":  8,
        "AveragePaid":  null,
        "AverageNetPaid":  null,
        "Stock":  null
    },
    {
        "Title":  "JUPITERS LEGACY",
        "Issue":  "2B",
        "Cover":  2,
        "TotalCost":  "2.44",
        "Mean":  2.4414285714285713,
        "AveragePrice":  1.9842857142857144,
        "CurrentPrice":  2.2800000000000002,
        "Minimum":  0.99,
        "Maximum":  2.9,
        "Count":  7,
        "AveragePaid":  null,
        "AverageNetPaid":  null,
        "Stock":  null
    },
    {
        "Title":  "JUPITERS LEGACY",
        "Issue":  "2C",
        "Cover":  2,
        "TotalCost":  "2.65",
        "Mean":  2.6500000000000004,
        "AveragePrice":  2.4000000000000004,
        "CurrentPrice":  2.4,
        "Minimum":  1.25,
        "Maximum":  2.95,
        "Count":  4,
        "AveragePaid":  null,
        "AverageNetPaid":  null,
        "Stock":  null
    },
    {
        "Title":  "JUPITERS LEGACY",
        "Issue":  "3A",
        "Cover":  3,
        "TotalCost":  "2.72",
        "Mean":  2.7185714285714289,
        "AveragePrice":  2.5757142857142861,
        "CurrentPrice":  2.3579999999999997,
        "Minimum":  1.5,
        "Maximum":  3.99,
        "Count":  7,
        "AveragePaid":  null,
        "AverageNetPaid":  null,
        "Stock":  null
    },
    {
        "Title":  "JUPITERS LEGACY",
        "Issue":  "3B",
        "Cover":  3,
        "TotalCost":  "2.28",
        "Mean":  2.2833333333333332,
        "AveragePrice":  1.9166666666666667,
        "CurrentPrice":  1.9166666666666667,
        "Minimum":  1.45,
        "Maximum":  2.5,
        "Count":  3,
        "AveragePaid":  null,
        "AverageNetPaid":  null,
        "Stock":  null
    },
    {
        "Title":  "JUPITERS LEGACY",
        "Issue":  "3C",
        "Cover":  3,
        "TotalCost":  "3.25",
        "Mean":  3.2466666666666666,
        "AveragePrice":  2.0966666666666667,
        "CurrentPrice":  2.0966666666666667,
        "Minimum":  1.5,
        "Maximum":  2.99,
        "Count":  3,
        "AveragePaid":  null,
        "AverageNetPaid":  null,
        "Stock":  null
    },
    {
        "Title":  "JUPITERS LEGACY",
        "Issue":  "4A",
        "Cover":  4,
        "TotalCost":  "2.80",
        "Mean":  2.8,
        "AveragePrice":  2.8,
        "CurrentPrice":  2.81,
        "Minimum":  2.25,
        "Maximum":  3.3,
        "Count":  7,
        "AveragePaid":  null,
        "AverageNetPaid":  null,
        "Stock":  null
    },
    {
        "Title":  "JUPITERS LEGACY",
        "Issue":  "4B",
        "Cover":  4,
        "TotalCost":  "2.21",
        "Mean":  2.208,
        "AveragePrice":  1.7880000000000003,
        "CurrentPrice":  1.7880000000000003,
        "Minimum":  0.99,
        "Maximum":  2.25,
        "Count":  5,
        "AveragePaid":  null,
        "AverageNetPaid":  null,
        "Stock":  null
    },
    {
        "Title":  "JUPITERS LEGACY",
        "Issue":  "4C",
        "Cover":  4,
        "TotalCost":  "2.91",
        "Mean":  2.91,
        "AveragePrice":  2.41,
        "CurrentPrice":  2.41,
        "Minimum":  0.99,
        "Maximum":  3.99,
        "Count":  3,
        "AveragePaid":  null,
        "AverageNetPaid":  null,
        "Stock":  null
    },
    {
        "Title":  "JUPITERS LEGACY",
        "Issue":  "SET",
        "Cover":  0,
        "TotalCost":  "6.23",
        "Mean":  6.2257142857142851,
        "AveragePrice":  4.8114285714285714,
        "CurrentPrice":  5.608,
        "Minimum":  0.99,
        "Maximum":  9.25,
        "Count":  14,
        "AveragePaid":  null,
        "AverageNetPaid":  null,
        "Stock":  null
    }
]
