[
    {
        "Title":  "OUTCAST",
        "Issue":  "1A",
        "Cover":  1,
        "TotalCost":  "8.13",
        "Mean":  8.1272511848341331,
        "AveragePrice":  7.1650236966824732,
        "CurrentPrice":  8.55,
        "Minimum":  1.44,
        "Maximum":  99.95,
        "Count":  211,
        "AveragePaid":  2.95,
        "AverageNetPaid":  2.95,
        "Stock":  1,
        "Date":  "\/Date(1432544704347)\/"
    },
    {
        "Title":  "OUTCAST",
        "Issue":  "1ACGC",
        "Cover":  1,
        "TotalCost":  "47.52",
        "Mean":  47.523333333333341,
        "AveragePrice":  41.667777777777779,
        "CurrentPrice":  53.8,
        "Minimum":  19,
        "Maximum":  77,
        "Count":  9,
        "AveragePaid":  null,
        "AverageNetPaid":  null,
        "Stock":  0,
        "Date":  "\/Date(1432544704495)\/"
    },
    {
        "Title":  "OUTCAST",
        "Issue":  "1B",
        "Cover":  1,
        "TotalCost":  "10.88",
        "Mean":  10.879999999999999,
        "AveragePrice":  6.18,
        "CurrentPrice":  6.18,
        "Minimum":  6.18,
        "Maximum":  6.18,
        "Count":  1,
        "AveragePaid":  null,
        "AverageNetPaid":  null,
        "Stock":  0,
        "Date":  "\/Date(1432544704642)\/"
    },
    {
        "Title":  "OUTCAST",
        "Issue":  "1C",
        "Cover":  1,
        "TotalCost":  "2.94",
        "Mean":  2.9433333333333334,
        "AveragePrice":  1.1933333333333336,
        "CurrentPrice":  1.1933333333333336,
        "Minimum":  0.49,
        "Maximum":  2.2,
        "Count":  3,
        "AveragePaid":  null,
        "AverageNetPaid":  null,
        "Stock":  0,
        "Date":  "\/Date(1432544704809)\/"
    },
    {
        "Title":  "OUTCAST",
        "Issue":  "1D",
        "Cover":  1,
        "TotalCost":  "2.15",
        "Mean":  2.1466666666666669,
        "AveragePrice":  2.1466666666666669,
        "CurrentPrice":  2.1466666666666665,
        "Minimum":  2.1,
        "Maximum":  2.24,
        "Count":  3,
        "AveragePaid":  2.1,
        "AverageNetPaid":  2.1,
        "Stock":  2,
        "Date":  "\/Date(1432544704962)\/"
    },
    {
        "Title":  "OUTCAST",
        "Issue":  "2A",
        "Cover":  2,
        "TotalCost":  "2.94",
        "Mean":  2.9360869565217391,
        "AveragePrice":  2.2926086956521736,
        "CurrentPrice":  1.276,
        "Minimum":  0.55,
        "Maximum":  3.5,
        "Count":  23,
        "AveragePaid":  2.25,
        "AverageNetPaid":  2.25,
        "Stock":  1,
        "Date":  "\/Date(1432544705187)\/"
    },
    {
        "Title":  "OUTCAST",
        "Issue":  "3A",
        "Cover":  3,
        "TotalCost":  "2.65",
        "Mean":  2.6538461538461537,
        "AveragePrice":  2.319230769230769,
        "CurrentPrice":  2.2279999999999998,
        "Minimum":  1.2,
        "Maximum":  3.4,
        "Count":  13,
        "AveragePaid":  2.1,
        "AverageNetPaid":  2.1,
        "Stock":  1,
        "Date":  "\/Date(1432544705384)\/"
    },
    {
        "Title":  "OUTCAST",
        "Issue":  "4A",
        "Cover":  4,
        "TotalCost":  "2.73",
        "Mean":  2.7275,
        "AveragePrice":  2.3025,
        "CurrentPrice":  2.054,
        "Minimum":  0.99,
        "Maximum":  3.4,
        "Count":  8,
        "AveragePaid":  2.1,
        "AverageNetPaid":  2.1,
        "Stock":  1,
        "Date":  "\/Date(1432544705576)\/"
    },
    {
        "Title":  "OUTCAST",
        "Issue":  "5",
        "Cover":  5,
        "TotalCost":  "3.00",
        "Mean":  3,
        "AveragePrice":  1.6,
        "CurrentPrice":  1.6,
        "Minimum":  1.6,
        "Maximum":  1.6,
        "Count":  1,
        "AveragePaid":  null,
        "AverageNetPaid":  null,
        "Stock":  0,
        "Date":  "\/Date(1432544705731)\/"
    },
    {
        "Title":  "OUTCAST",
        "Issue":  "6",
        "Cover":  6,
        "TotalCost":  "8.67",
        "Mean":  8.665,
        "AveragePrice":  5.965,
        "CurrentPrice":  5.965,
        "Minimum":  0.4,
        "Maximum":  11.53,
        "Count":  2,
        "AveragePaid":  null,
        "AverageNetPaid":  null,
        "Stock":  0,
        "Date":  "\/Date(1432544705921)\/"
    },
    {
        "Title":  "OUTCAST",
        "Issue":  "7",
        "Cover":  7,
        "TotalCost":  "2.15",
        "Mean":  2.15,
        "AveragePrice":  0.7,
        "CurrentPrice":  0.7,
        "Minimum":  0.4,
        "Maximum":  1,
        "Count":  2,
        "AveragePaid":  null,
        "AverageNetPaid":  null,
        "Stock":  0,
        "Date":  "\/Date(1432544706087)\/"
    },
    {
        "Title":  "OUTCAST",
        "Issue":  "8",
        "Cover":  8,
        "TotalCost":  "1.80",
        "Mean":  1.7999999999999998,
        "AveragePrice":  0.4,
        "CurrentPrice":  0.4,
        "Minimum":  0.4,
        "Maximum":  0.4,
        "Count":  1,
        "AveragePaid":  null,
        "AverageNetPaid":  null,
        "Stock":  0,
        "Date":  "\/Date(1432544706247)\/"
    },
    {
        "Title":  "OUTCAST",
        "Issue":  "POSTER",
        "Cover":  0,
        "TotalCost":  "7.47",
        "Mean":  7.4700000000000006,
        "AveragePrice":  7.4700000000000006,
        "CurrentPrice":  7.4700000000000006,
        "Minimum":  4.95,
        "Maximum":  9.99,
        "Count":  2,
        "AveragePaid":  null,
        "AverageNetPaid":  null,
        "Stock":  0,
        "Date":  "\/Date(1432544706405)\/"
    },
    {
        "Title":  "OUTCAST",
        "Issue":  "SET",
        "Cover":  0,
        "TotalCost":  "13.95",
        "Mean":  13.95123456790124,
        "AveragePrice":  12.041234567901238,
        "CurrentPrice":  20.3,
        "Minimum":  2,
        "Maximum":  30,
        "Count":  81,
        "AveragePaid":  null,
        "AverageNetPaid":  null,
        "Stock":  0,
        "Date":  "\/Date(1432544706894)\/"
    }
]
