[
    {
        "Title":  "THE DYING AND THE DEAD",
        "Issue":  "1",
        "Cover":  1,
        "TotalCost":  "3.40",
        "Mean":  3.40125,
        "AveragePrice":  2.8525,
        "CurrentPrice":  3.2820000000000009,
        "Minimum":  1.2,
        "Maximum":  3.99,
        "Count":  8,
        "AveragePaid":  2.1,
        "AverageNetPaid":  2.1,
        "Stock":  1,
        "Date":  "\/Date(1438017486974)\/"
    },
    {
        "Title":  "THE DYING AND THE DEAD",
        "Issue":  "2",
        "Cover":  2,
        "TotalCost":  "1.80",
        "Mean":  1.8,
        "AveragePrice":  1.8,
        "CurrentPrice":  1.8,
        "Minimum":  1.8,
        "Maximum":  1.8,
        "Count":  1,
        "AveragePaid":  1.8,
        "AverageNetPaid":  1.8,
        "Stock":  1,
        "Date":  "\/Date(1438017487094)\/"
    },
    {
        "Title":  "THE DYING AND THE DEAD",
        "Issue":  "4",
        "Cover":  4,
        "TotalCost":  "3.65",
        "Mean":  3.65,
        "AveragePrice":  3.65,
        "CurrentPrice":  3.65,
        "Minimum":  3.65,
        "Maximum":  3.65,
        "Count":  1,
        "AveragePaid":  null,
        "AverageNetPaid":  null,
        "Stock":  0,
        "Date":  "\/Date(1438017487214)\/"
    },
    {
        "Title":  "THE DYING AND THE DEAD",
        "Issue":  "5",
        "Cover":  5,
        "TotalCost":  "3.65",
        "Mean":  3.65,
        "AveragePrice":  3.65,
        "CurrentPrice":  3.65,
        "Minimum":  3.65,
        "Maximum":  3.65,
        "Count":  1,
        "AveragePaid":  null,
        "AverageNetPaid":  null,
        "Stock":  0,
        "Date":  "\/Date(1438017487334)\/"
    },
    {
        "Title":  "THE DYING AND THE DEAD",
        "Issue":  "SET",
        "Cover":  0,
        "TotalCost":  "4.89",
        "Mean":  4.8900000000000006,
        "AveragePrice":  3.99,
        "CurrentPrice":  3.99,
        "Minimum":  2.99,
        "Maximum":  4.99,
        "Count":  2,
        "AveragePaid":  null,
        "AverageNetPaid":  null,
        "Stock":  0,
        "Date":  "\/Date(1438017487464)\/"
    }
]
